[
  {
    "Id": 1,
    "Username": "EnKaz",
    "Name": "Enrei",
    "Lastname": "Kazuri",
    "Password": "prueba",
    "Account": [
      {
        "Id": 2,
        "NextId": 7,
        "UserId": 1,
        "Balance": 1512.50,
        "Transactions": [
          {
            "Id": 1,
            "AccountId": 2,
            "Name": "Nueva transaccion",
            "Amount": 560.0,
            "Date": "2023-01-22T21:28:03.4525845-04:00",
            "Category": {
              "Id": 2,
              "Name": "Gorritos"
            },
            "Description": "Es nueva",
            "TType": 1
          },
          {
            "Id": 2,
            "AccountId": 2,
            "Name": "transaccion",
            "Amount": 600.0,
            "Date": "2023-01-22T21:35:43.7878456-04:00",
            "Category": {
              "Id": 1,
              "Name": "Milk"
            },
            "Description": "Descripcion de la transaccion",
            "TType": 0
          },
          {
            "Id": 3,
            "AccountId": 2,
            "Name": "qw",
            "Amount": 50.0,
            "Date": "2023-01-22T21:41:26.7448726-04:00",
            "Category": {
              "Id": 1,
              "Name": "Milk"
            },
            "Description": "ddwq",
            "TType": 1
          },
          {
            "Id": 4,
            "AccountId": 2,
            "Name": "rgwwg",
            "Amount": 50.0,
            "Date": "2023-01-22T21:41:35.7338386-04:00",
            "Category": {
              "Id": 2,
              "Name": "Gorritos"
            },
            "Description": "gweeg",
            "TType": 1
          },
          {
            "Id": 5,
            "AccountId": 2,
            "Name": "wfefqf",
            "Amount": 2.0,
            "Date": "2023-01-22T21:41:45.0061341-04:00",
            "Category": {
              "Id": 5,
              "Name": "hello"
            },
            "Description": "qfdqq",
            "TType": 1
          },
          {
            "Id": 6,
            "AccountId": 2,
            "Name": "qwfqwgh",
            "Amount": 600.0,
            "Date": "2023-01-22T21:42:04.324339-04:00",
            "Category": {
              "Id": 2,
              "Name": "Gorritos"
            },
            "Description": "qgqagew",
            "TType": 0
          },
          {
            "Id": 7,
            "AccountId": 2,
            "Name": "gsdgh",
            "Amount": 800.0,
            "Date": "2023-01-22T21:51:48.3909338-04:00",
            "Category": {
              "Id": 2,
              "Name": "Gorritos"
            },
            "Description": "afadfadfg",
            "TType": 0
          }
        ]
      },
      {
        "Id": 4,
        "NextId": 7,
        "UserId": 1,
        "Balance": 579.7,
        "Transactions": []
      },
      {
        "Id": 6,
        "NextId": 7,
        "UserId": 1,
        "Balance": 1420.65,
        "Transactions": []
      }
    ]
  },
  {
    "Id": 2,
    "Username": "Pabloedud",
    "Name": "Pablo",
    "Lastname": "Diaz",
    "Password": "beastmaster64",
    "Account": [
      {
        "Id": 1,
        "NextId": 3,
        "UserId": 2,
        "Balance": 15000.00,
        "Transactions": [
          {
            "Id": 1,
            "AccountId": 1,
            "Name": "Recarga de mami",
            "Amount": 14000.00,
            "Date": "2023-01-22T21:13:31.4450009-04:00",
            "Category": {
              "Id": 1,
              "Name": "Videogames"
            },
            "Description": "Para el alquiler",
            "TType": 1
          }
        ]
      },
      {
        "Id": 2,
        "NextId": 3,
        "UserId": 2,
        "Balance": 5639.49,
        "Transactions": [
          {
            "Id": 1,
            "AccountId": 2,
            "Name": "Charge",
            "Amount": 5639.49,
            "Date": "2023-01-23T01:17:37.9461166-04:00",
            "Category": {
              "Id": 5,
              "Name": "hello"
            },
            "Description": "Charge from big sis",
            "TType": 1
          }
        ]
      }
    ]
  },
  {
    "Id": 3,
    "Username": "manu",
    "Name": "Manuel",
    "Lastname": "Mañón",
    "Password": "manu12",
    "Account": [
      {
        "Id": 1,
        "NextId": 2,
        "UserId": 3,
        "Balance": 1000.0,
        "Transactions": [
          {
            "Id": 1,
            "AccountId": 1,
            "Name": "pago",
            "Amount": 1000.0,
            "Date": "2023-01-22T21:42:56.5309529-04:00",
            "Category": {
              "Id": 5,
              "Name": "hello"
            },
            "Description": "",
            "TType": 1
          }
        ]
      }
    ]
  }
]